{"thName":"แบบจำลองเพื่อการจัดการทรัพยากรธรรมชาติ","code":"2303564","abbr":"MOD NAT RES MGT","enName":"MODELS FOR NATURAL RESOURCE MANAGEMENT","fac":"คณะวิทยาศาสตร์","dept":"ภาควิชาชีววิทยา","credit":3,"cHrs1":"LECT 2.0 CR + NL23 1.0 CR","cHrs2":"LECT 2.0 HR + PRAC 3.0 HR","prereq":"PRER 2303221,2303222 OR C.F.","midtermDate":"TDF","finalDate":"TDF","schedule":{"1":[{"method":"LECT","day":"TU","period":"16:00-18:00","building":"SCI10","room":"103","instructor":"STAFF","note":""},{"method":"PRAC","day":"TU WE","period":"16:00-19:00","building":"SCI10","room":"103","instructor":"STAFF","note":""}]}}