{"thName":"การจัดการทรัพยากรธรรมชาติและสิ่งแวดล้อมขั้นพื้นฐาน","code":"2308401","abbr":"FUND RES/ENVI MGT","enName":"FUNDAMENTAL NATURAL RESOURCES AND ENVIRONMENTAL MANAGEMENT","fac":"คณะวิทยาศาสตร์","dept":"ภาควิชาวิทยาศาสตร์สิ่งแวดล้อม","credit":3,"cHrs1":"LECT 3.0 CR","cHrs2":"LECT 3.0 HR","prereq":null,"midtermDate":"TDF","finalDate":["11 พ.ค. 2020","8:30","11:30"],"schedule":{"1":[{"method":"LECT","day":"TH","period":"9:00-12:00","building":"GENSC","room":"101","instructor":"NAN","note":""}]}}