{"thName":"เอกัตศึกษา 4","code":"2222594","abbr":"INDEPT STUD IV","enName":"INDEPENDENT STUDY IV","fac":"คณะอักษรศาสตร์","dept":"สาขาวิชาภาษาจีน","credit":3,"cHrs1":"LECT 1.0 CR + NL36 2.0 CR","cHrs2":"DISC 1.0 HR + IDPS 6.0 HR","prereq":"C.F.","midtermDate":"TDF","finalDate":"TDF","schedule":{"1":[{"method":"IDPS","day":"IA","period":"IA","building":"IA","room":"IA","instructor":"SCD","note":""},{"method":"DISC","day":"IA","period":"IA","building":"IA","room":"IA","instructor":"SCD","note":""}]}}