{"thName":"ระบบคอมพิวเตอร์และการบำรุงรักษา","code":"2765336","abbr":"COMP SYS MNTN","enName":"COMPUTER SYSTEMS AND MAINTENANCE","fac":"คณะครุศาสตร์","dept":"ภาควิชาเทคโนโลยีและสื่อสารการศึกษา","credit":3,"cHrs1":"LECT 2.0 CR + NL23 1.0 CR","cHrs2":"LECT 2.0 HR + PRAC 2.0 HR","prereq":null,"midtermDate":"TDF","finalDate":"TDF","schedule":{"1":[{"method":"LECT","day":"WE","period":"12:00-14:00","building":"EDU4","room":"403","instructor":"AUP","note":""},{"method":"PRAC","day":"WE","period":"14:00-16:00","building":"EDU4","room":"403","instructor":"AUP","note":""}]}}