{"thName":"วัสดุและกรรมวิธี 2","code":"3502290","abbr":"MATERL/PROCESS II","enName":"MATERIAL AND PROCESS II","fac":"คณะศิลปกรรมศาสตร์","dept":"ภาควิชานฤมิตศิลป์","credit":3,"cHrs1":"LECT 1.0 CR + NL36 2.0 CR","cHrs2":"LECT 1.0 HR + STU 5.0 HR","prereq":"PRER 3502190","midtermDate":"TDF","finalDate":"TDF","schedule":{"1":[{"method":"LECT","day":"TU","period":"9:00-10:00","building":"FA4","room":"301","instructor":"SLW","note":"CREATIVE ARTS"},{"method":"STU","day":"TU","period":"10:00-15:00","building":"FAA1","room":"A112","instructor":"SLW","note":""}],"2":[{"method":"LECT","day":"TU","period":"9:00-10:00","building":"BRK","room":"103","instructor":"PUK","note":"CREATIVE ARTS"},{"method":"STU","day":"TU","period":"10:00-15:00","building":"BRK","room":"103","instructor":"PUK","note":""}],"3":[{"method":"LECT","day":"TU","period":"9:00-10:00","building":"FAA1","room":"A115","instructor":"STAFF","note":""},{"method":"STU","day":"TU","period":"10:00-15:00","building":"FAA1","room":"A115","instructor":"STAFF","note":""}],"4":[{"method":"LECT","day":"TU","period":"9:00-10:00","building":"FAA1","room":"A115","instructor":"STAFF","note":""},{"method":"STU","day":"TU","period":"10:00-15:00","building":"FAA1","room":"A115","instructor":"STAFF","note":""}]}}