{"thName":"ทฤษฎีวงจรไฟฟ้า 2 และปฏิบัติการ","code":"2102214","abbr":"CIR THEORY II/LAB","enName":"CIRCUIT THEORY II AND LABORATORY","fac":"คณะวิศวกรรมศาสตร์","dept":"ภาควิชาวิศวกรรมไฟฟ้า","credit":3,"cHrs1":"LECT 3.0 CR","cHrs2":"LECT 3.0 HR + LAB 1.0 HR","prereq":"PRER 2102213 COREQ 2102201","midtermDate":"TDF","finalDate":["15 พ.ค. 2020","8:30","11:30"],"schedule":{"1":[{"method":"LECT","day":"TU TH","period":"9:30-11:00","building":"EN100","room":"502","instructor":"CPW","note":""},{"method":"LAB","day":"MO","period":"15:00-16:00","building":"ENG3","room":"309","instructor":"CPW,MWS,NHC","note":""}],"2":[{"method":"LECT","day":"TU TH","period":"9:30-11:00","building":"EN100","room":"504","instructor":"MWS","note":""},{"method":"LAB","day":"TU","period":"15:00-16:00","building":"ENG3","room":"301","instructor":"MWS,NHC,CPW","note":""}],"3":[{"method":"LECT","day":"TU TH","period":"9:30-11:00","building":"EN100","room":"501","instructor":"NHC","note":""},{"method":"LAB","day":"TH","period":"15:00-16:00","building":"ENG3","room":"301","instructor":"NHC,CPW,MWS","note":""}]}}