{"thName":"อุตสาหกรรมการผลิตสัตว์น้ำ","code":"3107512","abbr":"AQUACULT IND","enName":"AQUACULTURE INDUSTRY","fac":"คณะสัตวแพทยศาสตร์","dept":"ภาควิชาอายุรศาสตร์","credit":1,"cHrs1":"NL36 1.0 CR","cHrs2":"FWK 3.0 HR Year Course","prereq":null,"midtermDate":"TDF","finalDate":"TDF","schedule":{"1":[{"method":"FWK","day":"IA","period":"IA","building":"VET6","room":"IA","instructor":"STAFF","note":"VET"}],"2":[{"method":"FWK","day":"IA","period":"IA","building":"VET6","room":"IA","instructor":"STAFF","note":"VET"}],"3":[{"method":"FWK","day":"IA","period":"IA","building":"VET6","room":"IA","instructor":"STAFF","note":"VET"}],"4":[{"method":"FWK","day":"IA","period":"IA","building":"VET6","room":"IA","instructor":"STAFF","note":"VET"}],"5":[{"method":"FWK","day":"IA","period":"IA","building":"VET6","room":"IA","instructor":"STAFF","note":"VET"}],"6":[{"method":"FWK","day":"IA","period":"IA","building":"VET6","room":"IA","instructor":"STAFF","note":"VET"}],"7":[{"method":"FWK","day":"IA","period":"IA","building":"VET6","room":"IA","instructor":"STAFF","note":"VET"}],"8":[{"method":"FWK","day":"IA","period":"IA","building":"VET6","room":"IA","instructor":"STAFF","note":"VET"}],"9":[{"method":"FWK","day":"IA","period":"IA","building":"VET6","room":"IA","instructor":"STAFF","note":"VET"}],"10":[{"method":"FWK","day":"IA","period":"IA","building":"VET6","room":"IA","instructor":"STAFF","note":"VET"}],"11":[{"method":"FWK","day":"IA","period":"IA","building":"VET6","room":"IA","instructor":"STAFF","note":"VET"}],"12":[{"method":"FWK","day":"IA","period":"IA","building":"VET6","room":"IA","instructor":"STAFF","note":"VET"}],"13":[{"method":"FWK","day":"IA","period":"IA","building":"VET6","room":"IA","instructor":"STAFF","note":"VET"}],"14":[{"method":"FWK","day":"IA","period":"IA","building":"VET6","room":"IA","instructor":"STAFF","note":"VET"}],"15":[{"method":"FWK","day":"IA","period":"IA","building":"VET6","room":"IA","instructor":"STAFF","note":"VET"}],"16":[{"method":"FWK","day":"IA","period":"IA","building":"VET6","room":"IA","instructor":"STAFF","note":"VET"}]}}