{"thName":"ทักษะศัลยศาสตร์ 2","code":"3000687","abbr":"SKIL SURG II","enName":"SKILLS IN SURGERY II","fac":"คณะแพทยศาสตร์","dept":"ไม่สังกัดภาควิชา/เทียบเท่า","credit":3,"cHrs1":"NL23 3.0 CR","cHrs2":"PRAC 4.0 HR + TUT 2.0 HR","prereq":null,"midtermDate":"TDF","finalDate":"TDF","schedule":{"1":[{"method":"PRAC","day":"IA","period":"IA","building":"SIRIN","room":"IA","instructor":"STAFF","note":"6MED (CHULA)"},{"method":"TUT","day":"IA","period":"IA","building":"SIRIN","room":"IA","instructor":"STAFF","note":""}],"2":[{"method":"PRAC","day":"IA","period":"IA","building":"SIRIN","room":"IA","instructor":"STAFF","note":"6MED (CHULA)"},{"method":"TUT","day":"IA","period":"IA","building":"SIRIN","room":"IA","instructor":"STAFF","note":""}],"4":[{"method":"PRAC","day":"IA","period":"IA","building":"CHOL","room":"IA","instructor":"STAFF","note":"6MED (CHOL)"},{"method":"TUT","day":"IA","period":"IA","building":"CHOL","room":"IA","instructor":"STAFF","note":""}],"5":[{"method":"PRAC","day":"IA","period":"IA","building":"CHAN","room":"IA","instructor":"STAFF","note":"6MED (CHAN)"},{"method":"TUT","day":"IA","period":"IA","building":"CHAN","room":"IA","instructor":"STAFF","note":""}],"6":[{"method":"PRAC","day":"IA","period":"IA","building":"KUMKL","room":"IA","instructor":"STAFF","note":"6MED (BHUMIBOL HOSP)"},{"method":"TUT","day":"IA","period":"IA","building":"KUMKL","room":"IA","instructor":"STAFF","note":""}]}}