{"thName":"เภสัชวิทยาภูมิคุ้มกัน","code":"3010719","abbr":"IMMUNOPHARM","enName":"IMMUNOPHARMACOLOGY","fac":"คณะแพทยศาสตร์","dept":"ภาควิชาเภสัชวิทยา","credit":3,"cHrs1":"LECT 3.0 CR","cHrs2":"LECT 2.0 HR + DISC 1.0 HR","prereq":null,"midtermDate":"TDF","finalDate":"TDF","schedule":{"1":[{"method":"LECT","day":"IA","period":"IA","building":"PADTA","room":"IA","instructor":"STAFF","note":""},{"method":"DISC","day":"IA","period":"IA","building":"PADTA","room":"IA","instructor":"STAFF","note":""}]}}