{"thName":"อายุรศาสตร์สำหรับแพทย์เวชศาสตร์นิวเคลียร์","code":"3011749","abbr":"INT MED NM PHYS","enName":"INTERNAL MEDICINE FOR NUCLEAR MEDICINE PHYSICIAN","fac":"คณะแพทยศาสตร์","dept":"ภาควิชารังสีวิทยา","credit":2,"cHrs1":"LECT 1.0 CR + NL36 1.0 CR (S/U)","cHrs2":"LECT 1.0 HR + CLIN 3.0 HR Year Course","prereq":null,"midtermDate":"TDF","finalDate":"TDF","schedule":{"1":[{"method":"LECT","day":"IA","period":"IA","building":"POSA","room":"IA","instructor":"STAFF","note":""},{"method":"CLIN","day":"IA","period":"IA","building":"POSA","room":"IA","instructor":"STAFF","note":""}]}}