{"thName":"การวางแผนงานด้านการสร้างเสริมสุขภาพ","code":"3014866","abbr":"HLTH PROM PLNN","enName":"HEALTH PROMOTION PLANNING","fac":"คณะแพทยศาสตร์","dept":"ภาควิชาเวชศาสตร์ป้องกันและสังคม","credit":2,"cHrs1":"LECT 1.0 CR + NL23 1.0 CR","cHrs2":"LECT 1.0 HR + PRAC 3.0 HR","prereq":null,"midtermDate":"TDF","finalDate":"TDF","schedule":{"1":[{"method":"LECT","day":"TH","period":"10:00-11:00","building":"O.P.R","room":"1910C","instructor":"STAFF","note":""},{"method":"PRAC","day":"IA","period":"IA","building":"O.P.R","room":"IA","instructor":"STAFF","note":""}]}}