{"thName":"ศัลยศาสตร์ทารกแรกคลอด 1","code":"3015762","abbr":"NEO SURG I","enName":"NEONATAL SURGERY I","fac":"คณะแพทยศาสตร์","dept":"ภาควิชาศัลยศาสตร์","credit":3,"cHrs1":"LECT 1.0 CR + NL36 2.0 CR","cHrs2":"LECT 1.0 HR + FWK 6.0 HR Year Course","prereq":null,"midtermDate":"TDF","finalDate":"TDF","schedule":{"1":[{"method":"LECT","day":"IA","period":"IA","building":"SIRIN","room":"2","instructor":"STAFF","note":""},{"method":"FWK","day":"IA","period":"IA","building":"SIRIN","room":"2","instructor":"STAFF","note":""}]}}