{"thName":"การค้นคว้าวิจัยอิสระ","code":"2501644","abbr":"INDEPENDENT RES","enName":"INDEPENDENT RESEARCH","fac":"คณะสถาปัตยกรรมศาสตร์","dept":"ภาควิชาสถาปัตยกรรมศาสตร์","credit":3,"cHrs1":"NL23 3.0 CR","cHrs2":"LAB 9.0 HR","prereq":null,"midtermDate":"TDF","finalDate":"TDF","schedule":{"1":[{"method":"LAB","day":"IA","period":"IA","building":"NART","room":"IA","instructor":"PKT","note":"ARCH"}],"2":[{"method":"LAB","day":"IA","period":"IA","building":"NART","room":"IA","instructor":"WWP","note":"ARCH"}],"3":[{"method":"LAB","day":"IA","period":"IA","building":"NART","room":"IA","instructor":"BCS","note":"ARCH"}],"4":[{"method":"LAB","day":"IA","period":"IA","building":"NART","room":"IA","instructor":"TCN","note":"ARCH"}],"5":[{"method":"LAB","day":"IA","period":"IA","building":"NART","room":"IA","instructor":"WMD","note":"ARCH"}],"6":[{"method":"LAB","day":"IA","period":"IA","building":"NART","room":"IA","instructor":"TVR","note":"ARCH"}],"7":[{"method":"LAB","day":"IA","period":"IA","building":"NART","room":"IA","instructor":"KSR","note":"ARCH"}],"8":[{"method":"LAB","day":"IA","period":"IA","building":"NART","room":"IA","instructor":"ASP","note":"ARCH"}],"9":[{"method":"LAB","day":"IA","period":"IA","building":"NART","room":"IA","instructor":"CSW","note":"ARCH"}],"10":[{"method":"LAB","day":"IA","period":"IA","building":"NART","room":"IA","instructor":"VIR","note":"ARCH"}],"11":[{"method":"LAB","day":"IA","period":"IA","building":"NART","room":"IA","instructor":"PSU","note":"ARCH"}],"12":[{"method":"LAB","day":"IA","period":"IA","building":"NART","room":"IA","instructor":"TTK","note":"ARCH"}],"13":[{"method":"LAB","day":"IA","period":"IA","building":"NART","room":"IA","instructor":"PSY","note":"ARCH"}],"14":[{"method":"LAB","day":"IA","period":"IA","building":"NART","room":"IA","instructor":"PPT","note":"ARCH"}],"15":[{"method":"LAB","day":"IA","period":"IA","building":"NART","room":"IA","instructor":"WIN","note":"ARCH"}],"16":[{"method":"LAB","day":"IA","period":"IA","building":"NART","room":"IA","instructor":"VBK","note":"ARCH"}],"19":[{"method":"LAB","day":"IA","period":"IA","building":"NART","room":"IA","instructor":"CCB","note":"ARCH"}],"20":[{"method":"LAB","day":"IA","period":"IA","building":"IA","room":"IA","instructor":"CFP","note":"ARCH"}]}}